{"title": "Alogliptin plus voglibose in Japanese patients with type 2 diabetes: a randomized, double-blind, placebo-controlled trial with an open-label, long-term extension.", "abstract": "To compare the efficacy and safety of alogliptin and placebo as add-on therapy in Japanese patients with type 2 diabetes who experienced inadequate glycemic control on voglibose plus diet/exercise therapy. During an 8 week screening phase, patients aged ≥ 20 years were stabilized on voglibose 0.2 mg three times daily plus diet/exercise therapy. Those with HbA1c between ≥ 6.9% and <10.4% were randomly assigned to 12 weeks' double-blind treatment with once daily alogliptin 12.5 or 25 mg, or placebo. The primary endpoint was the change in HbA1c at 12 weeks from baseline. Patients then entered an open-label, 40 week extension trial (patients in the placebo group were randomly allocated to alogliptin 12.5 or 25 mg). www.clinicaltrials.gov ; pivotal trial NCT01263483; Long term trial NCT01263509. Least square mean change in HbA1c after 12 weeks' therapy from baseline (primary endpoint) was significantly greater in the alogliptin 12.5 mg (-0.96%; P < 0.0001) and 25 mg (-0.93%; P < 0.0001) groups compared with placebo (+0.06%). This was associated with statistically significant improvements in other measures of glycemic control, in particular sustained reductions in fasting plasma glucose and postprandial plasma glucose. These benefits were maintained for the duration of the 1 year study and, importantly, they were achieved without detrimental effects on tolerability/safety. In particular, there was no increase in the rate of hypoglycemia and almost no changes in mean body weight. Addition of once daily alogliptin to voglibose monotherapy in Japanese patients with uncontrolled type 2 diabetes produced clinically significant improvements in glycemic control, and was well tolerated.", "year": 2011, "doi": "10.1185/03007995.2011.614936", "journal": "Current medical research and opinion"}