{"title": "Trajectories of Function and Symptom Change in Desvenlafaxine Clinical Trials: Toward Personalized Treatment for Depression.", "abstract": "Heterogeneity has been documented in trajectories of symptom change during antidepressant treatment for major depressive disorder (MDD). It is unclear whether distinct trajectories of change exist for functioning during antidepressant treatment. This analysis explored distinct trajectories of functioning in MDD and tested whether they corresponded to trajectories of symptom change. Data were from 4317 patients and were pooled from 9 randomized placebo-controlled trials. Growth mixture modeling was used to identify trajectories of Hamilton Rating Scale for Depression (HRSD) and Sheehan Disability Scale (SDS) for placebo- and desvenlafaxine-treated patients. Three trajectories were identified for symptoms (HRSD) in patients receiving placebo (mean reduction baseline to week 8, -18.4 [most favorable] to -2.6 points [least favorable]). Four HRSD trajectories were identified for patients receiving desvenlafaxine (mean reduction from baseline to week 8, -17.2 [most favorable] to -2.6 points [least favorable]). Four trajectories were identified for functioning (SDS) in patients receiving placebo (mean reduction baseline to week 8, -13.6 [most favorable] to -0.8 points [least favorable]), and 3 for desvenlafaxine (-12.8 to -1.4 points, respectively). Percentages of agreement between most favorable HRSD and SDS trajectories were 75% (placebo) and 85% (desvenlafaxine), and for least favorable trajectories were 88% (placebo) and 80% (desvenlafaxine). Distinct trajectories of change based on symptoms and functioning were identified among patients with MDD receiving desvenlafaxine and among patients with MDD receiving placebo. Differentiating subpopulations of patients has the potential to provide a more personalized treatment of patients with MDD.ClinicalTrials.govIdentifiers: NCT00072774; NCT00277823; NCT00300378; NCT00384033; NCT00798707; NCT00863798; NCT01121484; NCT00824291; NCT01432457.", "year": null, "doi": "10.1097/JCP.0000000000001435", "journal": "Journal of clinical psychopharmacology"}