{
  "topic": {
    "stem": "ADALIMUMAB_JIA_AUTO",
    "name": "Adalimumab in JIA",
    "ncts": [
      "NCT00783510",
      "NCT02840175",
      "NCT00048542",
      "NCT00775437"
    ],
    "drug_patterns": [
      "adalimumab"
    ],
    "condition_patterns": [
      "juvenile idiopathic"
    ]
  },
  "trials": [
    {
      "gates": {
        "A_aact_exists": true,
        "B_drug_in_intvs": true,
        "C_condition_in_aact": true,
        "D_pmid_topic_match": false,
        "E_two_arms": false,
        "F_primary_outcome_known": true
      },
      "extracted": {
        "nct": "NCT00783510",
        "aact_title": "Juvenile Idiopathic Arthritis (JIA) Registry",
        "aact_acronym": "STRIVE",
        "start_date": "2008-07-11",
        "primary_completion_date": "2024-02-01",
        "aact_intvs": [
          "adalimumab",
          "methotrexate"
        ],
        "aact_conditions": [
          "jia",
          "juvenile idiopathic arthritis"
        ],
        "pmid": null,
        "aact_per_arm_counts": {},
        "aact_primary_outcome_measure": "Incidence of Serious Adverse Events (SAEs)",
        "aact_outcome_count_rows": []
      }
    },
    {
      "gates": {
        "A_aact_exists": true,
        "B_drug_in_intvs": true,
        "C_condition_in_aact": true,
        "D_pmid_topic_match": false,
        "E_two_arms": false,
        "F_primary_outcome_known": true
      },
      "extracted": {
        "nct": "NCT02840175",
        "aact_title": "Treatment Tapering in JIA With Inactive Disease",
        "aact_acronym": "AJIBIOREM",
        "start_date": "2017-05-18",
        "primary_completion_date": "2019-10-29",
        "aact_intvs": [
          "etanercept",
          "adalimumab",
          "abatacept"
        ],
        "aact_conditions": [
          "juvenile idiopathic arthritis"
        ],
        "pmid": null,
        "aact_per_arm_counts": {},
        "aact_primary_outcome_measure": "Persistence of inactive disease",
        "aact_outcome_count_rows": []
      }
    },
    {
      "gates": {
        "A_aact_exists": true,
        "B_drug_in_intvs": true,
        "C_condition_in_aact": true,
        "D_pmid_topic_match": true,
        "E_two_arms": true,
        "F_primary_outcome_known": true
      },
      "extracted": {
        "nct": "NCT00048542",
        "aact_title": "Study of Human Anti-TNF Monoclonal Antibody Adalimumab in Children With Polyarticular Juvenile Idiopathic Arthritis (JIA)",
        "aact_acronym": "",
        "start_date": "2002-09-30",
        "primary_completion_date": "2005-01-31",
        "aact_intvs": [
          "double-blind adalimumab/placebo + mtx",
          "double-blind adalimumab/placebo",
          "ole bsa adalimumab +/- mtx"
        ],
        "aact_conditions": [
          "arthritis, juvenile idiopathic"
        ],
        "pmid": "30054164",
        "pubmed_year": 2018,
        "pubmed_doi": "10.1016/j.jpeds.2018.05.042",
        "aact_per_arm_counts": {
          "BG000": 38,
          "BG001": 37,
          "BG002": 30,
          "BG003": 28
        },
        "aact_primary_outcome_measure": "Number of Subjects in the Non-MTX Stratum With Disease Flare During the Double-Blind Phase",
        "aact_outcome_count_rows": [
          [
            "OG000",
            "13.0"
          ],
          [
            "OG001",
            "20.0"
          ],
          [
            "OG000",
            "80.0"
          ],
          [
            "OG001",
            "64.0"
          ],
          [
            "OG000",
            "14.0"
          ],
          [
            "OG001",
            "24.0"
          ],
          [
            "OG000",
            "90.0"
          ],
          [
            "OG001",
            "78.6"
          ],
          [
            "OG000",
            "83.3"
          ],
          [
            "OG001",
            "64.3"
          ]
        ]
      }
    },
    {
      "gates": {
        "A_aact_exists": true,
        "B_drug_in_intvs": true,
        "C_condition_in_aact": true,
        "D_pmid_topic_match": true,
        "E_two_arms": false,
        "F_primary_outcome_known": true
      },
      "extracted": {
        "nct": "NCT00775437",
        "aact_title": "Active Juvenile Idiopathic Arthritis (JIA) Compassionate Use",
        "aact_acronym": "",
        "start_date": "2009-03-31",
        "primary_completion_date": "2013-03-31",
        "aact_intvs": [
          "adalimumab"
        ],
        "aact_conditions": [
          "juvenile idiopathic arthritis"
        ],
        "pmid": "30054164",
        "pubmed_year": 2018,
        "pubmed_doi": "10.1016/j.jpeds.2018.05.042",
        "aact_per_arm_counts": {
          "BG000": 32
        },
        "aact_primary_outcome_measure": "Number of Participants With Treatment-Emergent Adverse Events (TEAEs)",
        "aact_outcome_count_rows": [
          [
            "OG000",
            "29.0"
          ],
          [
            "OG000",
            "5.0"
          ],
          [
            "OG000",
            "93.5"
          ],
          [
            "OG000",
            "90.6"
          ],
          [
            "OG000",
            "93.5"
          ],
          [
            "OG000",
            "90.0"
          ],
          [
            "OG000",
            "84.4"
          ],
          [
            "OG000",
            "90.3"
          ],
          [
            "OG000",
            "92.6"
          ],
          [
            "OG000",
            "78.1"
          ]
        ]
      }
    }
  ],
  "n_total": 4,
  "n_pass_all": 1,
  "verdict": "NOT_VIABLE",
  "pass_rate": 0.25
}