{
  "topic": {
    "stem": "TUCATINIB_BREAST_AUTO",
    "name": "Tucatinib in HER2+ breast",
    "ncts": [
      "NCT06961331",
      "NCT04721977",
      "NCT05458674",
      "NCT05800275",
      "NCT06439693",
      "NCT04539938",
      "NCT04220203",
      "NCT05583110"
    ],
    "drug_patterns": [
      "tucatinib"
    ],
    "condition_patterns": [
      "breast"
    ]
  },
  "trials": [
    {
      "gates": {
        "A_aact_exists": true,
        "B_drug_in_intvs": true,
        "C_condition_in_aact": true,
        "D_pmid_topic_match": false,
        "E_two_arms": false,
        "F_primary_outcome_known": true
      },
      "extracted": {
        "nct": "NCT06961331",
        "aact_title": "Real World-clinical Outcomes of Tucatinib, Trastuzumab, and Capecitabine Following Trastuzumab Deruxtecan (T-DXd) for the Treatment of HER2-positive Metastatic Breast Cancer.",
        "aact_acronym": "",
        "start_date": "2025-05-07",
        "primary_completion_date": "2025-09-25",
        "aact_intvs": [
          "tucatinib",
          "trastuzumab",
          "capecitabine"
        ],
        "aact_conditions": [
          "metastatic her2+ advanced breast cancer"
        ],
        "pmid": null,
        "aact_per_arm_counts": {},
        "aact_primary_outcome_measure": "Time to Next Treatment",
        "aact_outcome_count_rows": []
      }
    },
    {
      "gates": {
        "A_aact_exists": true,
        "B_drug_in_intvs": true,
        "C_condition_in_aact": true,
        "D_pmid_topic_match": false,
        "E_two_arms": false,
        "F_primary_outcome_known": true
      },
      "extracted": {
        "nct": "NCT04721977",
        "aact_title": "A Study of Tucatinib (MK-7119) in Combination With Trastuzumab and Capecitabine in Participants With Previously Treated Locally Advanced Unresectable or Metastatic Human Epidermal Growth Factor Receptor 2 Positive (HER2+) Breast Carcinoma (MK-7119-001)",
        "aact_acronym": "",
        "start_date": "2021-04-08",
        "primary_completion_date": "2023-07-17",
        "aact_intvs": [
          "tucatinib",
          "trastuzumab",
          "capecitabine"
        ],
        "aact_conditions": [
          "breast cancer"
        ],
        "pmid": null,
        "aact_per_arm_counts": {
          "BG000": 66
        },
        "aact_primary_outcome_measure": "Confirmed Objective Response Rate(cORR) Per Response Evaluation Criteria in Solid Tumors (RECIST) Version 1.1 Determined by Independent Central Review (ICR): Japanese Participants",
        "aact_outcome_count_rows": [
          [
            "OG000",
            "35.4"
          ]
        ]
      }
    },
    {
      "gates": {
        "A_aact_exists": true,
        "B_drug_in_intvs": true,
        "C_condition_in_aact": true,
        "D_pmid_topic_match": false,
        "E_two_arms": false,
        "F_primary_outcome_known": true
      },
      "extracted": {
        "nct": "NCT05458674",
        "aact_title": "Tucatinib+Trastuzumab+Eribulin in HER2+ MBC",
        "aact_acronym": "",
        "start_date": "2024-01-30",
        "primary_completion_date": "2027-06-01",
        "aact_intvs": [
          "tucatinib",
          "eribulin",
          "trastuzumab"
        ],
        "aact_conditions": [
          "breast cancer",
          "pretreated unresectable locally advanced or metastatic her2+ breast cancer"
        ],
        "pmid": null,
        "aact_per_arm_counts": {},
        "aact_primary_outcome_measure": "To assess the safety and tolerability of tucatinib in combination with eribulin and trastuzumab in patients with unresectable or recurrent metastatic HER2+ breast cancer who have had prior treatment w",
        "aact_outcome_count_rows": []
      }
    },
    {
      "gates": {
        "A_aact_exists": true,
        "B_drug_in_intvs": true,
        "C_condition_in_aact": true,
        "D_pmid_topic_match": false,
        "E_two_arms": false,
        "F_primary_outcome_known": true
      },
      "extracted": {
        "nct": "NCT05800275",
        "aact_title": "Capecitabine, Tucatinib, and Intrathecal Trastuzumab for Breast Cancer Patients With Leptomeningeal Disease",
        "aact_acronym": "ETIC-LM",
        "start_date": "2023-12-18",
        "primary_completion_date": "2026-12-31",
        "aact_intvs": [
          "tucatinib oral tablet",
          "capecitabine tablets",
          "trastuzumab injection"
        ],
        "aact_conditions": [
          "her2-positive metastatic breast cancer",
          "leptomeningeal disease",
          "leptomeningeal metastasis"
        ],
        "pmid": null,
        "aact_per_arm_counts": {},
        "aact_primary_outcome_measure": "overall survival rate at 12 months",
        "aact_outcome_count_rows": []
      }
    },
    {
      "gates": {
        "A_aact_exists": true,
        "B_drug_in_intvs": true,
        "C_condition_in_aact": true,
        "D_pmid_topic_match": false,
        "E_two_arms": false,
        "F_primary_outcome_known": true
      },
      "extracted": {
        "nct": "NCT06439693",
        "aact_title": "The SAPPHO Study: Sequential Therapy With Curative Intent in de Novo HER2+ Metastatic Breast Cancer",
        "aact_acronym": "",
        "start_date": "2024-08-08",
        "primary_completion_date": "2030-03-30",
        "aact_intvs": [
          "nab-paclitaxel",
          "paclitaxel",
          "docetaxel"
        ],
        "aact_conditions": [
          "breast cancer",
          "breast cancer female",
          "breast cancer metastatic"
        ],
        "pmid": null,
        "aact_per_arm_counts": {},
        "aact_primary_outcome_measure": "Disease Free Survival at 4 Years (DFS4)",
        "aact_outcome_count_rows": []
      }
    },
    {
      "gates": {
        "A_aact_exists": true,
        "B_drug_in_intvs": true,
        "C_condition_in_aact": true,
        "D_pmid_topic_match": false,
        "E_two_arms": false,
        "F_primary_outcome_known": true
      },
      "extracted": {
        "nct": "NCT04539938",
        "aact_title": "A Study of Tucatinib Plus Trastuzumab Deruxtecan in HER2+ Breast Cancer",
        "aact_acronym": "HER2CLIMB-04",
        "start_date": "2020-12-01",
        "primary_completion_date": "2024-07-15",
        "aact_intvs": [
          "tucatinib",
          "trastuzumab deruxtecan"
        ],
        "aact_conditions": [
          "her2 positive breast cancer"
        ],
        "pmid": null,
        "aact_per_arm_counts": {
          "BG000": 70
        },
        "aact_primary_outcome_measure": "Confirmed Objective Response Rate (cORR) Per Response Evaluation Criteria in Solid Tumors (RECIST) Version 1.1 According to Investigator (INV) Assessment",
        "aact_outcome_count_rows": [
          [
            "OG000",
            "51.4"
          ],
          [
            "OG000",
            "94.3"
          ],
          [
            "OG000",
            "70.0"
          ],
          [
            "OG000",
            "25.0"
          ],
          [
            "OG000",
            "6.0"
          ],
          [
            "OG000",
            "17.0"
          ],
          [
            "OG000",
            "38.0"
          ],
          [
            "OG000",
            "6.0"
          ],
          [
            "OG000",
            "3.0"
          ],
          [
            "OG000",
            "67.0"
          ]
        ]
      }
    },
    {
      "gates": {
        "A_aact_exists": true,
        "B_drug_in_intvs": true,
        "C_condition_in_aact": true,
        "D_pmid_topic_match": false,
        "E_two_arms": false,
        "F_primary_outcome_known": false
      },
      "extracted": {
        "nct": "NCT04220203",
        "aact_title": "Treatment Protocol of Tucatinib With Capecitabine and Trastuzumab in Patients With Unresectable Previously Treated HER2+ Breast Cancer",
        "aact_acronym": "",
        "start_date": "",
        "primary_completion_date": "",
        "aact_intvs": [
          "tucatinib",
          "capecitabine",
          "trastuzumab"
        ],
        "aact_conditions": [
          "her2-positive breast cancer"
        ],
        "pmid": null,
        "aact_per_arm_counts": {},
        "aact_primary_outcome_measure": "",
        "aact_outcome_count_rows": []
      }
    },
    {
      "gates": {
        "A_aact_exists": true,
        "B_drug_in_intvs": true,
        "C_condition_in_aact": true,
        "D_pmid_topic_match": false,
        "E_two_arms": false,
        "F_primary_outcome_known": true
      },
      "extracted": {
        "nct": "NCT05583110",
        "aact_title": "Efficacy and Safety of the Combination of Trastuzumab Plus TUCAtinib Plus viNorelbine in Patients With HER2-positive Non-resectable Locally Advanced or Metastatic Breast Cancer",
        "aact_acronym": "TrasTUCAN",
        "start_date": "2023-03-08",
        "primary_completion_date": "2025-05-30",
        "aact_intvs": [
          "tucatinib",
          "trastuzumab",
          "vinorelbine"
        ],
        "aact_conditions": [
          "her2-positive metastatic breast cancer",
          "locally advanced her2 positive breast carcinoma"
        ],
        "pmid": null,
        "aact_per_arm_counts": {},
        "aact_primary_outcome_measure": "Objective Response Rate (ORR)",
        "aact_outcome_count_rows": []
      }
    }
  ],
  "n_total": 8,
  "n_pass_all": 0,
  "verdict": "NOT_VIABLE",
  "pass_rate": 0.0
}