{
  "review": "SMA_TREATMENTS_BROAD_REVIEW",
  "audit_completed_at": "2026-05-13T10:40:01.484734+00:00",
  "classification": "LOW_CONCERN",
  "fabrication_risk_score": 0.392,
  "n_trials": 12,
  "score_components": {
    "E_no_evidence": 0.75,
    "P_null_pmid": 0.667,
    "N_nulled_nct": 0.0,
    "A_agent_flag_density": 0.0,
    "C_cross_review": 0.0,
    "V_residual_single_arm": 0.0,
    "X_generic_name": 0.0
  },
  "already_quarantined": false,
  "audit_rounds_touched": [
    "R19_completion",
    "R23_acronym",
    "R6b_internal",
    "R6c_internal"
  ],
  "fixes_applied": [
    {
      "round": "R6b_internal",
      "nct": "NCT02122952",
      "op": "NULL_BASELINE_N",
      "reason": "NULLED_BASELINE_N"
    },
    {
      "round": "R6b_internal",
      "nct": "NCT02122952",
      "op": "NULL_BASELINE_N",
      "reason": ""
    },
    {
      "round": "R6c_internal",
      "nct": "NCT03505099",
      "op": "NULL_PMID",
      "reason": "NULLED_PMID"
    },
    {
      "round": "R6c_internal",
      "nct": "NCT03505099",
      "op": "NULL_PMID",
      "reason": ""
    },
    {
      "round": "R19_completion",
      "nct": "NCT02386553",
      "op": "NULL_YEAR",
      "reason": "NULLED_YEAR"
    },
    {
      "round": "R19_completion",
      "nct": "NCT03032172",
      "op": "NULL_YEAR",
      "reason": "NULLED_YEAR"
    },
    {
      "round": "R19_completion",
      "nct": "NCT02386553",
      "op": "NULL_YEAR",
      "reason": ""
    },
    {
      "round": "R19_completion",
      "nct": "NCT03032172",
      "op": "NULL_YEAR",
      "reason": ""
    },
    {
      "round": "R23_acronym",
      "nct": "NCT03461289",
      "op": "NULL_PMID",
      "reason": "PMID_ALREADY_NULL"
    },
    {
      "round": "R23_acronym",
      "nct": "NCT03505099",
      "op": "NULL_PMID",
      "reason": "PMID_ALREADY_NULL"
    },
    {
      "round": "R23_acronym",
      "nct": "NCT02122952",
      "op": "NULL_PMID",
      "reason": "NULLED_PMID"
    }
  ],
  "n_fixes_applied": 11,
  "ground_truth_sources": [
    "AACT 2026-04-12 (Clinical Trials Transformation Initiative)",
    "PubMed E-utilities (NCBI)",
    "PMC OAI full-text (NCBI)",
    "Multi-agent consensus (≥2-of-3 gate, R1-R3 + R4 + 8-agent)",
    "Internal cross-consistency (R6abc)",
    "Published landmark trial values (R5)",
    "Published reference meta-analyses (R5b)"
  ],
  "methodology": "outputs/extraction_audit/FINAL_INTEGRITY_REPORT_V2.md",
  "truthcert_hmac_sha256": "64a0a8a40b31f0e82db01be6aae2d1ad5b1a1e41d577c08c9380f8dbb372865b",
  "truthcert_key_id": "791652a76703ca25"
}