{
  "realData": {
    "NCT00042289": {
      "name": "TRIAL",
      "baseline": {
        "n": 56
      },
      "pmid": "34076612",
      "year": 2021,
      "group": "atazanavir/cobicistat",
      "tE": 7,
      "tN": 26,
      "cE": 9,
      "cN": 30,
      "estimandType": "OR",
      "publishedHR": null,
      "hrLCI": null,
      "hrUCI": null,
      "evidence": [
        {
          "source": "AACT 2026-04-12 + PubMed",
          "text": "NCT NCT00042289: PK Parameter: Area Under the Curve From 0 to 12 Hours (AUC12) With Median (IQR) for ARVs and TB Drugs",
          "sourceUrl": "https://clinicaltrials.gov/study/NCT00042289"
        }
      ]
    },
    "NCT01695954": {
      "name": "TRIAL",
      "baseline": {
        "n": 34
      },
      "pmid": "25202920",
      "year": 2014,
      "group": "pitavastatin",
      "tE": null,
      "tN": 18,
      "cE": null,
      "cN": 16,
      "estimandType": "OR",
      "publishedHR": null,
      "hrLCI": null,
      "hrUCI": null,
      "evidence": [
        {
          "source": "AACT 2026-04-12 + PubMed",
          "text": "NCT NCT01695954: AUC",
          "sourceUrl": "https://clinicaltrials.gov/study/NCT01695954"
        }
      ]
    }
  },
  "nctAcronyms": {}
}