{
  "file": "HYDROCORTISONE_SEPTIC_SHOCK_REVIEW.html",
  "realData": {
    "NCT01448109": {
      "name": "ADRENAL (Venkatesh 2018)",
      "baseline": {
        "n": 3658
      },
      "pmid": "29347874",
      "phase": "III",
      "year": 2018,
      "tE": 511,
      "tN": 1832,
      "cE": 526,
      "cN": 1826,
      "group": "Venkatesh B, Finfer S, Cohen J, et al. NEJM 2018;378:797-808 (PMID 29347874). NHMRC Australia + multiple national funding-sponsored multinational double-blind randomized trial in n=3,800 critically ill mechanically-ventilated septic-shock patients across 69 ICUs in 5 countries (Australia, UK, NZ, Saudi Arabia, Denmark). Randomized 1:1 to (A) hydrocortisone 200 mg/day continuous IV infusion x 7 days (n=1,832) vs (B) matching placebo (n=1,826). PRIMARY: 90-day all-cause mortality. RESULT: 511/1,832 (27.9%) hydrocortisone vs 526/1,826 (28.8%) placebo — RR 0.96 (95% CI 0.86-1.08; OR 0.95, P=0.50) — NULL on mortality. Faster shock reversal (3 vs 4 days) and shorter MV (6 vs 7 days), more hyperglycemia and infection but no mortality benefit. Africa relevance: indirect (no African ICUs); ADRENAL is the largest single septic-shock corticosteroid trial and the comparator benchmark for any African septic-shock NMA.",
      "estimandType": "RR",
      "publishedHR": 0.96,
      "hrLCI": 0.86,
      "hrUCI": 1.08,
      "pubHR": 0.96,
      "allOutcomes": [
        {
          "shortLabel": "MORT_90D",
          "title": "90-day all-cause mortality (HC vs placebo)",
          "tE": 511,
          "cE": 526,
          "type": "PRIMARY",
          "matchScore": 100,
          "effect": 0.96,
          "lci": 0.86,
          "uci": 1.08,
          "estimandType": "RR"
        },
        {
          "shortLabel": "SHOCK_REV",
          "title": "Time to shock resolution (median days)",
          "tE": 3,
          "cE": 4,
          "type": "SECONDARY",
          "matchScore": 90,
          "effect": 0.69,
          "lci": 0.62,
          "uci": 0.78,
          "estimandType": "HR"
        }
      ],
      "rob": [
        "low",
        "low",
        "low",
        "low",
        "low"
      ],
      "snippet": "Source: Venkatesh B, Finfer S, Cohen J, et al. Adjunctive Glucocorticoid Therapy in Patients with Septic Shock (ADRENAL). NEJM 2018;378:797-808. PMID 29347874. DOI 10.1056/NEJMoa1705835.",
      "sourceUrl": "https://doi.org/10.1056/NEJMoa1705835",
      "ctgovUrl": "https://clinicaltrials.gov/study/NCT01448109"
    },
    "NCT00625209": {
      "name": "APROCCHSS (Annane 2018)",
      "baseline": {
        "n": 1241
      },
      "pmid": "29490185",
      "phase": "IV",
      "year": 2018,
      "tE": 264,
      "tN": 614,
      "cE": 308,
      "cN": 627,
      "group": "Annane D, Renault A, Brun-Buisson C, et al. NEJM 2018;378:809-818 (PMID 29490185). French Ministry of Health-sponsored multicenter double-blind 2x2 factorial randomized trial in n=1,241 ICU patients with septic shock across 34 French ICUs from 2008-2015. Initial factorial randomized to hydrocortisone 50mg q6h IV + fludrocortisone 50ug PO QD (HF) vs placebo, AND drotrecogin-alfa-activated (APC) vs placebo (APC arm dropped 2011 after withdrawal). Final analysis: HF (n=614) vs placebo (n=627). PRIMARY: 90-day all-cause mortality. RESULT: 264/614 (43.0%) HF vs 308/627 (49.1%) placebo — RR 0.88 (95% CI 0.78-0.99; P=0.03) — HF SUPERIOR. Number-needed-to-treat = 16 to prevent 1 death at 90d. CONTRAST WITH ADRENAL (null mortality): APROCCHSS used q6h bolus + fludrocortisone (mineralocorticoid) and enrolled higher-severity sicker patients (mean SOFA 12 vs 11 in ADRENAL; >50% on RRT). Drove ESICM 2017+2024 conditional recommendation for HC in refractory shock.",
      "estimandType": "RR",
      "publishedHR": 0.88,
      "hrLCI": 0.78,
      "hrUCI": 0.99,
      "pubHR": 0.88,
      "allOutcomes": [
        {
          "shortLabel": "MORT_90D",
          "title": "90-day all-cause mortality (HF vs placebo)",
          "tE": 264,
          "cE": 308,
          "type": "PRIMARY",
          "matchScore": 100,
          "effect": 0.88,
          "lci": 0.78,
          "uci": 0.99,
          "estimandType": "RR"
        },
        {
          "shortLabel": "VFD",
          "title": "Vasopressor-free days at d28 (median)",
          "tE": 17,
          "cE": 15,
          "type": "SECONDARY",
          "matchScore": 90,
          "effect": 1.13,
          "lci": 1.04,
          "uci": 1.23,
          "estimandType": "RR"
        }
      ],
      "rob": [
        "low",
        "low",
        "low",
        "low",
        "low"
      ],
      "snippet": "Source: Annane D, Renault A, Brun-Buisson C, et al. Hydrocortisone plus Fludrocortisone for Adults with Septic Shock (APROCCHSS). NEJM 2018;378:809-818. PMID 29490185. DOI 10.1056/NEJMoa1705716.",
      "sourceUrl": "https://doi.org/10.1056/NEJMoa1705716",
      "ctgovUrl": "https://clinicaltrials.gov/study/NCT00625209"
    },
    "NCT00670254": {
      "name": "HYPRESS (Keh 2016)",
      "baseline": {
        "n": 380
      },
      "pmid": "27695824",
      "phase": "III",
      "year": 2016,
      "tE": 21,
      "tN": 190,
      "cE": 29,
      "cN": 190,
      "group": "Keh D, Trips E, Marx G, et al; SepNet–Critical Care Trials Group. JAMA 2016;316:1775-1785 (PMID 27695822). German Federal Ministry of Education and Research-sponsored multicenter double-blind randomized trial in n=380 patients with severe sepsis BUT NO SHOCK across 34 German ICUs 2009-2013. Randomized 1:1 to (A) hydrocortisone 200mg/day continuous infusion x 5d then taper (n=190) vs (B) matching placebo (n=190). PRIMARY: development of septic SHOCK within 14 days. RESULT: 21/190 (11.1%) HC vs 29/190 (15.3%) placebo — difference -4.2pp (95% CI -10.0 to +1.6; P=0.16) — NULL: HC did NOT prevent shock progression. SECONDARY mortality 28d: similar between arms. KEY MESSAGE: hydrocortisone NOT indicated to PREVENT shock — only justified in established refractory shock. Drove SCCM 2017 guidance NOT to use HC for sepsis without shock.",
      "estimandType": "RR",
      "publishedHR": 0.72,
      "hrLCI": 0.43,
      "hrUCI": 1.22,
      "pubHR": 0.72,
      "allOutcomes": [
        {
          "shortLabel": "SHOCK_14D",
          "title": "Septic shock onset within 14d (HC vs placebo)",
          "tE": 21,
          "cE": 29,
          "type": "PRIMARY",
          "matchScore": 100,
          "effect": 0.72,
          "lci": 0.43,
          "uci": 1.22,
          "estimandType": "RR"
        },
        {
          "shortLabel": "MORT_180D",
          "title": "180-day all-cause mortality (HC vs placebo)",
          "tE": 53,
          "cE": 53,
          "type": "SECONDARY",
          "matchScore": 90,
          "effect": 1.0,
          "lci": 0.71,
          "uci": 1.41,
          "estimandType": "RR"
        }
      ],
      "rob": [
        "low",
        "low",
        "low",
        "low",
        "low"
      ],
      "snippet": "Source: Keh D, Trips E, Marx G, et al. Effect of Hydrocortisone on Development of Shock Among Patients With Severe Sepsis: The HYPRESS Randomized Clinical Trial. JAMA 2016;316:1775-1785. PMID 27695822. DOI 10.1001/jama.2016.14799.",
      "sourceUrl": "https://doi.org/10.1001/jama.2016.14799",
      "ctgovUrl": "https://clinicaltrials.gov/study/NCT00670254"
    }
  },
  "NMA_CONFIG": {
    "treatments": [
      "Dapagliflozin",
      "Empagliflozin",
      "Sotagliflozin",
      "Placebo"
    ],
    "comparisons": [
      {
        "t1": "Dapagliflozin",
        "t2": "Placebo",
        "trials": [
          "NCT03036124",
          "NCT03619213"
        ]
      },
      {
        "t1": "Empagliflozin",
        "t2": "Placebo",
        "trials": [
          "NCT03057977",
          "NCT03057951"
        ]
      },
      {
        "t1": "Sotagliflozin",
        "t2": "Placebo",
        "trials": [
          "NCT03521934",
          "NCT03315143"
        ]
      }
    ],
    "outcome": "cvdeath_hhf",
    "outcome_label": "Cardiovascular death or hospitalisation for heart failure (primary composite, trial-specific primary endpoint)",
    "note": "k=6 Pbo-controlled Phase 3 trials; each SGLT2i has 2 direct Pbo-anchored trials (precision-adequate). Network is a Pbo-star (no closed loops). Indirect Dapa-vs-Empa, Dapa-vs-Sota, Empa-vs-Sota contrasts computed through the Pbo anchor. Consistency test not defined in star-only networks; report pairwise direct estimates + indirect contrasts with explicit declaration."
  },
  "title": "RapidMeta ITU | Hydrocortisone in Septic Shock NMA &mdash; ADRENAL + APROCCHSS + HYPRESS v0.1",
  "h1": "hfref quadruple therapy \\u2014 Patient Summary"
}