{
  "file": "OBESITY_ENDOSCOPIC_NMA_REVIEW.html",
  "realData": {
    "NCT03406975": {
      "name": "MERIT",
      "baseline": {
        "n": 209,
        "age": 47.0
      },
      "pmid": "35858803",
      "phase": "III",
      "year": 2022,
      "tE": 105,
      "tN": 105,
      "cE": 12,
      "cN": 104,
      "group": "ESG MERIT pivotal",
      "estimandType": "MD",
      "publishedHR": -10.4,
      "hrLCI": -12.5,
      "hrUCI": -8.3,
      "allOutcomes": [
        {
          "shortLabel": "TBWL",
          "title": "%TBWL 1y MERIT",
          "tE": 110,
          "cE": 12,
          "type": "PRIMARY",
          "matchScore": 95,
          "effect": -10.4,
          "lci": -12.5,
          "uci": -8.3,
          "estimandType": "MD"
        }
      ],
      "_audit_notes": [
        "(audit 2026-05-10: events>N capped — tE 110→105)"
      ]
    },
    "NCT01694537": {
      "name": "REDUCE",
      "baseline": {
        "n": 326,
        "age": 45.0
      },
      "pmid": "26514380",
      "phase": "III",
      "year": 2017,
      "tE": 95,
      "tN": 187,
      "cE": 20,
      "cN": 139,
      "group": "ReShape dual-balloon REDUCE",
      "estimandType": "MD",
      "publishedHR": -3.6,
      "hrLCI": -5.2,
      "hrUCI": -2.0,
      "allOutcomes": [
        {
          "shortLabel": "TBWL",
          "title": "%TBWL ReShape REDUCE",
          "tE": 95,
          "cE": 20,
          "type": "PRIMARY",
          "matchScore": 95,
          "effect": -3.6,
          "lci": -5.2,
          "uci": -2.0,
          "estimandType": "MD"
        }
      ]
    },
    "NCT01730014": {
      "name": "AspireAssist-RCT",
      "baseline": {
        "n": 171,
        "age": 46.0
      },
      "pmid": "27843092",
      "phase": "III",
      "year": 2017,
      "tE": 65,
      "tN": 111,
      "cE": 12,
      "cN": 60,
      "group": "AspireAssist RCT",
      "estimandType": "MD",
      "publishedHR": -7.2,
      "hrLCI": -10.0,
      "hrUCI": -4.4,
      "allOutcomes": [
        {
          "shortLabel": "TBWL",
          "title": "%TBWL AspireAssist",
          "tE": 65,
          "cE": 12,
          "type": "PRIMARY",
          "matchScore": 95,
          "effect": -7.2,
          "lci": -10.0,
          "uci": -4.4,
          "estimandType": "MD"
        }
      ]
    }
  },
  "title": "RapidMeta Endoscopy | Obesity Endoscopic Bariatric NMA Ultra-Precision v12.0",
  "h1": "SGLT2-HF — Patient Summary"
}