{
  "file": "VAMOROLONE_DMD_REVIEW.html",
  "realData": {
    "NCT03439670": {
      "name": "NCT03439670",
      "baseline": {
        "n": 56
      },
      "pmid": "36036925",
      "phase": "III",
      "year": 2022,
      "tE": null,
      "tN": 28,
      "cE": null,
      "cN": 28,
      "group": "Vamorolone",
      "estimandType": "OR",
      "publishedHR": null,
      "hrLCI": null,
      "hrUCI": null,
      "evidence": [
        {
          "label": "Primary outcome (AACT)",
          "source": "AACT 2026-04-12",
          "text": "Efficacy Measured by Time to Stand Test (TTSTAND) Velocity in Rises/Second Change From Baseline",
          "sourceUrl": "https://clinicaltrials.gov/study/NCT03439670"
        }
      ]
    },
    "NCT03038399": {
      "name": "NCT03038399",
      "baseline": {
        "n": 23
      },
      "pmid": "32956407",
      "phase": "III",
      "year": 2020,
      "tE": 4,
      "tN": 11,
      "cE": 14,
      "cN": 12,
      "group": "Vamorolone 0.25 mg/day/day",
      "estimandType": "OR",
      "publishedHR": null,
      "hrLCI": null,
      "hrUCI": null,
      "evidence": [
        {
          "label": "Primary outcome (AACT)",
          "source": "AACT 2026-04-12",
          "text": "Number of Participants With Treatment-related Adverse Events as Assessed by CTCAE Version 4.03",
          "sourceUrl": "https://clinicaltrials.gov/study/NCT03038399"
        }
      ]
    }
  },
  "title": "Vamorolone in Duchenne — RapidMeta (audit-first)",
  "h1": "Vamorolone in Duchenne"
}